agent_evolve/__init__.py
agent_evolve/__main__.py
agent_evolve/config.py
agent_evolve/dashboard.py
agent_evolve/evolve_decorator.py
agent_evolve/example_decorated_tools.py
agent_evolve/extract_commented_evolve.py
agent_evolve/extract_decorated_tools.py
agent_evolve/extract_tools.py
agent_evolve/generate_evaluators.py
agent_evolve/generate_openevolve_configs.py
agent_evolve/generate_training_data.py
agent_evolve/run_openevolve.py
agent_evolve/tracking/__init__.py
agent_evolve/tracking/analysis.py
agent_evolve/tracking/config.py
agent_evolve/tracking/context.py
agent_evolve/tracking/decorator.py
agent_evolve/tracking/extractors.py
agent_evolve/tracking/models.py
agent_evolve/tracking/sqlite_storage.py
agent_evolve/tracking/storage.py
agent_evolve/tracking/tracker.py
agent_evolve-1.0.0.dist-info/licenses/LICENSE
agent_evolve-1.0.0.dist-info/METADATA
agent_evolve-1.0.0.dist-info/WHEEL
agent_evolve-1.0.0.dist-info/entry_points.txt
agent_evolve-1.0.0.dist-info/top_level.txt
agent_evolve-1.0.0.dist-info/RECORD
