Metadata-Version: 2.4
Name: agent-evolve
Version: 1.0.0
Summary: A comprehensive toolkit for evolving and tracking AI agents
Author: Agent Evolution Team
Author-email: Agent Evolution Team <team@agentevolve.com>
License: MIT
Project-URL: Homepage, https://github.com/yourusername/agent-evolve
Project-URL: Documentation, https://agent-evolve.readthedocs.io/
Project-URL: Repository, https://github.com/yourusername/agent-evolve.git
Project-URL: Bug Tracker, https://github.com/yourusername/agent-evolve/issues
Keywords: ai,agent,evolution,machine-learning,optimization
Classifier: Development Status :: 4 - Beta
Classifier: Intended Audience :: Developers
Classifier: License :: OSI Approved :: MIT License
Classifier: Operating System :: OS Independent
Classifier: Programming Language :: Python :: 3
Classifier: Programming Language :: Python :: 3.8
Classifier: Programming Language :: Python :: 3.9
Classifier: Programming Language :: Python :: 3.10
Classifier: Programming Language :: Python :: 3.11
Classifier: Programming Language :: Python :: 3.12
Classifier: Programming Language :: Python :: 3.13
Requires-Python: >=3.8
License-File: LICENSE
Requires-Dist: streamlit>=1.28.0
Requires-Dist: streamlit-ace>=0.1.1
Requires-Dist: plotly>=5.0.0
Requires-Dist: pandas>=1.3.0
Requires-Dist: openai>=1.0.0
Requires-Dist: openevolve>=0.1.0
Requires-Dist: langchain-openai>=0.1.0
Requires-Dist: langchain-core>=0.1.0
Requires-Dist: python-dotenv>=0.19.0
Requires-Dist: yfinance>=0.2.0
Provides-Extra: dev
Requires-Dist: pytest>=6.0; extra == "dev"
Requires-Dist: pytest-asyncio; extra == "dev"
Requires-Dist: black; extra == "dev"
Requires-Dist: flake8; extra == "dev"
Dynamic: author
Dynamic: license-file
Dynamic: requires-python
